json_post/__init__.py
json_post/cli.py
json_post-0.2.dist-info/LICENSE
json_post-0.2.dist-info/METADATA
json_post-0.2.dist-info/WHEEL
json_post-0.2.dist-info/entry_points.txt
json_post-0.2.dist-info/top_level.txt
json_post-0.2.dist-info/RECORD
