Metadata-Version: 2.1
Name: json-post
Version: 0.2
Summary: Tool for posting JSON to an API, broken into pages
Home-page: https://github.com/simonw/json-post
Author: Simon Willison
License: Apache License, Version 2.0
Project-URL: Issues, https://github.com/simonw/json-post/issues
Project-URL: CI, https://github.com/simonw/json-post/actions
Project-URL: Changelog, https://github.com/simonw/json-post/releases
Platform: UNKNOWN
Requires-Python: >=3.6
Requires-Dist: click
Requires-Dist: httpx
Provides-Extra: test
Requires-Dist: pytest ; extra == 'test'
Requires-Dist: pytest-httpx ; extra == 'test'
